<?xml version="1.0" encoding="UTF-8"?>
<feature
      id="com.cougaarsoftware.cougaar.ide"
      label="Cougaar Integrated Development Environment"
      version="1.3.1.1"
      provider-name="Cougaar Software, Inc."
      nl="en"
      image="cougaar_logo.gif">

   <description url="http://cougaaride.cougaar.org/">
      Cougaar Integrated Development Environment
   </description>

   <copyright>
      Copyright (C) 2003, Cougaar Software, Inc.
   </copyright>

   <license url="LICENSE.txt">
      GNU GENERAL PUBLIC LICENSE
Version 2, June 1991
Copyright (C) 1989, 1991 Free Software Foundation, Inc.
59 Temple Place, Suite 330, Boston, MA  02111-1307  USA
Everyone is permitted to copy and distribute verbatim copies
of this license document, but changing it is not allowed.
Preamble
The licenses for most software are designed to take away your
freedom to share and change it.  By contrast, the GNU General
Public
License is intended to guarantee your freedom to share and change
free
software--to make sure the software is free for all its users.
This
General Public License applies to most of the Free Software
Foundation
   </license>

   <requires>
      <import plugin="org.eclipse.ui.ide"/>
      <import plugin="org.eclipse.jface.text"/>
      <import plugin="org.eclipse.ui.editors"/>
      <import plugin="org.eclipse.core.runtime"/>
      <import plugin="org.eclipse.core.resources"/>
      <import plugin="org.eclipse.ui"/>
      <import plugin="org.eclipse.jdt.core"/>
      <import plugin="org.eclipse.jdt.ui"/>
      <import plugin="org.eclipse.swt"/>
      <import plugin="org.eclipse.ui.workbench.texteditor"/>
      <import plugin="org.eclipse.jdt.launching"/>
      <import plugin="org.eclipse.debug.core"/>
      <import plugin="org.eclipse.debug.ui"/>
      <import plugin="org.eclipse.jdt.debug"/>
      <import plugin="org.eclipse.jdt.debug.ui"/>
   </requires>

   <plugin
         id="com.cougaarsoftware.cougaar.ide"
         download-size="0"
         install-size="0"
         version="1.3.1"/>

   <plugin
         id="com.cougaarsoftware.cougaar.ide.core"
         download-size="0"
         install-size="0"
         version="1.3.1"/>

   <plugin
         id="com.cougaarsoftware.cougaar.ide.launcher.core"
         download-size="0"
         install-size="0"
         version="1.3.1"/>

   <plugin
         id="com.cougaarsoftware.cougaar.ide.launcher.ui"
         download-size="0"
         install-size="0"
         version="1.3.1"/>

   <plugin
         id="com.cougaarsoftware.cougaar.ide.ui"
         download-size="0"
         install-size="0"
         version="1.3.1"/>

</feature>
